{"arguments": {"argv": ["%PORT%"]}, "programs": [{"output": [{"status": "SET"}, {"status": "SET"}, {"status": "SET"}, {"status": "RETURNING", "output": {"y": "llo", "x": "hello", "z": "hellohe"}}], "program": "as principal admin password \"admin\" do\nset x = \"hello\"\nset y = split(x,\"..\")\nset z = concat(x,y.fst)\nreturn { x=x, y=y.snd, z=z }\n***\n"}, {"output": [{"status": "SET"}, {"status": "SET"}, {"status": "SET"}, {"status": "SET"}, {"status": "SET"}, {"status": "SET"}, {"status": "SET"}, {"status": "APPEND"}, {"status": "APPEND"}, {"status": "APPEND"}, {"status": "APPEND"}, {"status": "APPEND"}, {"status": "RETURNING", "output": [{"snd": "HELLO", "fst": ""}, {"snd": "", "fst": "HELLO"}, "HELLO", "HELLO", "hello"]}], "program": "as principal admin password \"admin\" do\nset x = \"HELLO\"\nset y = split(x,\"\")\nset z = split(x,\".....X\")\nset x1 = concat(z.fst,z.snd)\nset x2 = concat(y.fst,y.snd)\nset x3 = tolower(x)\nset records = []\nappend to records with y\nappend to records with z \nappend to records with x1\nappend to records with x2\nappend to records with x3\nreturn records\n***\n"}]}